dicom_bone/__init__.py
dicom_bone/point_cloud_abs.py
dicom_bone/show_point_cloud.py
dicom_bone-0.0.2.dist-info/LICENSE
dicom_bone-0.0.2.dist-info/METADATA
dicom_bone-0.0.2.dist-info/WHEEL
dicom_bone-0.0.2.dist-info/top_level.txt
dicom_bone-0.0.2.dist-info/RECORD
