Metadata-Version: 2.2
Name: dicom_bone
Version: 0.0.2
Summary: get bone point cloud from dicom folder
Author-email: GGN_2015 <premierbob@qq.com>
License: MIT License
Classifier: Programming Language :: Python :: 3
Classifier: License :: OSI Approved :: MIT License
Classifier: Operating System :: OS Independent
Requires-Python: >=3.10
License-File: LICENSE
Requires-Dist: pydicom>=3.0.1
Requires-Dist: SimpleITK>=2.4.1
Requires-Dist: numpy>=2.2.3
Requires-Dist: scikit-image>=0.25.2
Requires-Dist: tqdm>=4.67.1
Requires-Dist: vtk>=9.3.1
